audiotoken/__init__.py
audiotoken/configs.py
audiotoken/core.py
audiotoken/datasets.py
audiotoken/decoder.py
audiotoken/encoder.py
audiotoken/gpt2_model.py
audiotoken/logger.py
audiotoken/modeling_wav2vec2_bert.py
audiotoken/processors.py
audiotoken/utils.py
test/__init__.py
test/convert_audio.py
test/utils.py
audiotoken-0.3.1.dist-info/LICENSE
audiotoken-0.3.1.dist-info/METADATA
audiotoken-0.3.1.dist-info/WHEEL
audiotoken-0.3.1.dist-info/dependency_links.txt
audiotoken-0.3.1.dist-info/entry_points.txt
audiotoken-0.3.1.dist-info/top_level.txt
audiotoken-0.3.1.dist-info/RECORD
